{
	"format_version": "1.8.0",
	"animations": {
		"animation.cloning.new": {
			"loop": "hold_on_last_frame",
			"animation_length": 5,
			"bones": {
				"root": {
					"rotation": {
						"2.5": [0, 0, 0],
						"3.4583": ["-math.sin(q.anim_time * 3000) * 3", 0, "math.cos(q.anim_time * 2000) * 3"],
						"3.5417": [0, 0, 0]
					},
					"scale": {
						"0.0": [0, 0, 0],
						"0.0417": [0.06, 0.06, 0.06],
						"0.0833": [0.2, 0.2, 0.2],
						"0.1667": [0.8, 0.8, 0.8],
						"0.2083": [0.94, 0.94, 0.94],
						"0.25": [1, 1, 1],
						"2.5": [1, 1, 1],
						"2.6667": [1.0075, 1.0075, 1.0075],
						"2.8333": [1.02, 1.02, 1.02],
						"3.0": [1.045, 1.045, 1.045],
						"3.1667": [1.08, 1.08, 1.08],
						"3.3333": [1.13, 1.13, 1.13],
						"3.4583": [1.2, 1.2, 1.2],
						"3.5417": {
							"pre": [1.6, 1.6, 1.6],
							"post": [0, 0, 0]
						},
						"4.0": [0, 0, 0]
					}
				},
				"LeftArm": {
					"rotation": {
						"0.0": [0, 0, 0],
						"0.5": [0, 0, -15],
						"3.375": [0, 0, -15],
						"3.4167": [-0.74907, 0.2913, -122.49984]
					},
					"position": [0, 0, 0]
				},
				"RightArm": {
					"rotation": {
						"0.0": [0, 0, 0],
						"0.5": [0, 0, 15],
						"3.375": [0, 0, 15],
						"3.4167": [-0.76715, -0.27922, 124.99983]
					},
					"position": [0, 0, 0]
				}
			},
			"particle_effects": {
				"3.5": {
					"effect": "smokimpact",
					"locator": "cros"
				}
			}
		},
		"animation.cloning.newas": {
			"loop": "hold_on_last_frame",
			"animation_length": 3.5,
			"particle_effects": {
				"3.5": {
					"effect": "smokimpact",
					"locator": "cros"
				}
			}
		},
		"animation.cloning.newasa": {
			"loop": true,
			"bones": {
				"RightLeg": {
					"rotation": [25.51, 67.73, 27.27],
					"position": [0.5, 0, 2.42]
				},
				"LeftLeg": {
					"rotation": [-9.29, 21.36, -8.45],
					"position": [-0.82, 0, -1.98]
				},
				"Body": {
					"rotation": [0, -50, 0],
					"position": [0, 0, 0]
				},
				"LeftArm": {
					"rotation": [-46.99, -15.67, -32.86]
				},
				"Head": {
					"rotation": [0, 45, 0]
				},
				"RightArm": {
					"rotation": [246.67, 47.81, 338.52],
					"position": [-1.51, -0.35, -1.8]
				}
			}
		}
	}
}